README.md
setup.cfg
setup.py
s2reader/__init__.py
s2reader/exceptions.py
s2reader/s2reader.py
s2reader.egg-info/PKG-INFO
s2reader.egg-info/SOURCES.txt
s2reader.egg-info/dependency_links.txt
s2reader.egg-info/entry_points.txt
s2reader.egg-info/requires.txt
s2reader.egg-info/top_level.txt
s2reader/cli/__init__.py
s2reader/cli/inspect.py
s2reader/cli/transform.py