Metadata-Version: 1.1
Name: s2reader
Version: 0.5
Summary: simple metadata reader for Sentinel-2 SAFE files
Home-page: https://github.com/ungarj/s2reader
Author: Joachim Ungar
Author-email: joachim.ungar@gmail.com
License: MIT
Platform: UNKNOWN
Classifier: Development Status :: 3 - Alpha
Classifier: Intended Audience :: Developers
Classifier: Topic :: Scientific/Engineering :: GIS
Classifier: License :: OSI Approved :: MIT License
Classifier: Programming Language :: Python :: 2.7
